[
    {
        "nid": "Foolish_Whisper",
        "name": "Foolish Whisper",
        "desc": "",
        "icon_nid": "ZessDynamiteSkillsysSuneohair",
        "icon_index": [
            0,
            88
        ],
        "components": [
            [
                "target_enemy",
                null
            ],
            [
                "min_range",
                1
            ],
            [
                "max_range",
                4
            ],
            [
                "status_after_combat_on_hit",
                "S_Silenced"
            ],
            [
                "mana_cost",
                26
            ],
            [
                "map_hit_sfx",
                "Silence1"
            ],
            [
                "enemy_blast_aoe",
                1
            ],
            [
                "exp",
                25
            ]
        ]
    }
]